LICENSE.txt
MANIFEST.in
README.rst
setup.py
hal_impl/__init__.py
hal_impl/distutils.py
hal_impl/fndef.py
hal_impl/libwpiHal.so
hal_impl/libwpiutil.so
hal_impl/types.py
hal_impl/version.py
robotpy_hal_roborio.egg-info/PKG-INFO
robotpy_hal_roborio.egg-info/SOURCES.txt
robotpy_hal_roborio.egg-info/dependency_links.txt
robotpy_hal_roborio.egg-info/requires.txt
robotpy_hal_roborio.egg-info/top_level.txt