Metadata-Version: 1.1
Name: robotpy-hal-roborio
Version: 2018.0.11
Summary: WPILib HAL layer for roboRIO platform
Home-page: https://github.com/robotpy
Author: Peter Johnson, Dustin Spicuzza
Author-email: robotpy@googlegroups.com
License: BSD License
Keywords: frc first robotics hal can
Platform: UNKNOWN
Classifier: Development Status :: 5 - Production/Stable
Classifier: Intended Audience :: Developers
Classifier: Intended Audience :: Education
Classifier: License :: OSI Approved :: BSD License
Classifier: Operating System :: POSIX :: Linux
Classifier: Programming Language :: Python :: 3.5
Classifier: Programming Language :: Python :: 3.6
Classifier: Topic :: Scientific/Engineering
